{
	"name": "Кафедра СЭГЗС",
	"email": "kafedra_zs@mail.ru",
	"phoneForTel": "+7-495-939-36-21",
	"phoneFormatted": "+7(495) 939-3621",
	"address": {
		"lineOne": "ГСП-1, РФ, Москва, Ленинские горы,",
		"lineTwo": "МГУ имени М.В. Ломоносова, Географический факультет, кафедра СЭГЗС",
		"city": "Москва,",
		"state": "РФ,",
		"zip": "119991",
		"mapLink": "https://yandex.ru/maps/org/glavnoye_zdaniye_mgu_imeni_m_v_lomonosova/30052052914/?ll=37.530822%2C55.702952&z=17"
	},
	"domain": "www.segzs.app"
}
